medusa/__init__.py
medusa/backup_cluster.py
medusa/backup_manager.py
medusa/backup_node.py
medusa/cassandra_utils.py
medusa/config.py
medusa/download.py
medusa/fetch_tokenmap.py
medusa/filtering.py
medusa/host_man.py
medusa/index.py
medusa/listing.py
medusa/medusacli.py
medusa/monitoring/__init__.py
medusa/monitoring/abstract.py
medusa/monitoring/dogstatsd.py
medusa/monitoring/local.py
medusa/monitoring/noop.py
medusa/network/__init__.py
medusa/network/hostname_resolver.py
medusa/nodetool.py
medusa/orchestration.py
medusa/purge.py
medusa/purge_decommissioned.py
medusa/report_latest.py
medusa/restore_cluster.py
medusa/restore_node.py
medusa/schema.py
medusa/scripts/__init__.py
medusa/scripts/medusa-wrapper.sh
medusa/scripts/medusa_wrapper.py
medusa/service/__init__.py
medusa/service/grpc/__init__.py
medusa/service/grpc/client.py
medusa/service/grpc/medusa.proto
medusa/service/grpc/medusa_pb2.py
medusa/service/grpc/medusa_pb2_grpc.py
medusa/service/grpc/restore.py
medusa/service/grpc/server.py
medusa/service/snapshot/__init__.py
medusa/service/snapshot/abstract_snapshot_service.py
medusa/service/snapshot/ccm_snapshot_service.py
medusa/service/snapshot/jolokia_snapshot_service.py
medusa/service/snapshot/management_api_snapshot_service.py
medusa/service/snapshot/nodetool_snapshot_service.py
medusa/status.py
medusa/storage/__init__.py
medusa/storage/abstract_storage.py
medusa/storage/azure_storage.py
medusa/storage/cluster_backup.py
medusa/storage/google_storage.py
medusa/storage/local_storage.py
medusa/storage/node_backup.py
medusa/storage/s3_base_storage.py
medusa/storage/s3_rgw.py
medusa/storage/s3_storage.py
medusa/utils.py
medusa/verify.py
medusa/verify_restore.py
medusa-example.ini
cassandra_medusa-0.27.0.dist-info/LICENSE
cassandra_medusa-0.27.0.dist-info/METADATA
cassandra_medusa-0.27.0.dist-info/NOTICE
cassandra_medusa-0.27.0.dist-info/WHEEL
cassandra_medusa-0.27.0.dist-info/entry_points.txt
cassandra_medusa-0.27.0.dist-info/RECORD
