Metadata-Version: 2.1
Name: cassandra-medusa
Version: 0.27.0
Summary: Apache Cassandra backup and restore tool
Home-page: https://github.com/thelastpickle/cassandra-medusa
License: Apache
Author: The Last Pickle
Author-email: medusa@thelastpickle.com
Requires-Python: >=3.10.0,<3.13
Classifier: Development Status :: 4 - Beta
Classifier: Environment :: Console
Classifier: Intended Audience :: System Administrators
Classifier: License :: OSI Approved :: Apache Software License
Classifier: License :: Other/Proprietary License
Classifier: Programming Language :: Python :: 3
Classifier: Programming Language :: Python :: 3.10
Classifier: Programming Language :: Python :: 3.11
Classifier: Programming Language :: Python :: 3.12
Classifier: Programming Language :: Python :: 3.9
Classifier: Topic :: Database
Classifier: Topic :: System :: Archiving :: Backup
Requires-Dist: PyYAML (==6.0.1)
Requires-Dist: aiofiles (==23.2.1)
Requires-Dist: aiohttp (==3.13.3)
Requires-Dist: asyncio (==3.4.3)
Requires-Dist: azure-core (==1.29.4)
Requires-Dist: azure-identity (==1.16.1)
Requires-Dist: azure-storage-blob (==12.17.0)
Requires-Dist: boto3 (==1.40.41)
Requires-Dist: botocore (==1.40.41)
Requires-Dist: cassandra-driver (==3.29.2)
Requires-Dist: click (==8.1.7)
Requires-Dist: click-aliases (==1.0.1)
Requires-Dist: cryptography (==44.0.1)
Requires-Dist: datadog (==0.47.0)
Requires-Dist: dnspython (==2.6.1)
Requires-Dist: fasteners (==0.16)
Requires-Dist: gcloud-aio-storage (==9.6.0)
Requires-Dist: gevent (==25.4.1)
Requires-Dist: greenlet (==3.2.0)
Requires-Dist: lockfile (==0.12.2)
Requires-Dist: parallel-ssh (==2.13.0)
Requires-Dist: psutil (==5.9.6)
Requires-Dist: pyOpenSSL (==25.0.0)
Requires-Dist: pycryptodome (==3.19.1)
Requires-Dist: python-dateutil (==2.8.1)
Requires-Dist: requests (==2.32.4)
Requires-Dist: setuptools (==78.1.1)
Requires-Dist: ssh-python (==1.1.0)
Requires-Dist: ssh2-python (==1.1.1)
Requires-Dist: tenacity (==9.1.2)
Requires-Dist: urllib3 (==2.6.0)
Requires-Dist: wheel (==0.38.1)
